algo_beast_core/__init__.py
algo_beast_core/app.py
algo_beast_core/broker_manager.py
algo_beast_core/chart.py
algo_beast_core/session.py
algo_beast_core/store.py
algo_beast_core/brokers/__init__.py
algo_beast_core/brokers/algo_beast_broker.py
algo_beast_core/brokers/fyers_broker.py
algo_beast_core/helpers/__init__.py
algo_beast_core/helpers/parse_args.py
algo_beast_core/helpers/validate_session.py
algo_beast_core-0.0.5.dist-info/LICENSE
algo_beast_core-0.0.5.dist-info/METADATA
algo_beast_core-0.0.5.dist-info/WHEEL
algo_beast_core-0.0.5.dist-info/top_level.txt
algo_beast_core-0.0.5.dist-info/RECORD
