Metadata-Version: 2.1
Name: algo-beast-core
Version: 0.0.5
Summary: AlgoBeast Core Engine
Home-page: https://github.com/krunaldodiya/algo-beast-core
Author: Krunal Dodiya
Author-email: kunal.dodiya1@gmail.com
Classifier: Programming Language :: Python :: 3
Classifier: Operating System :: OS Independent
License-File: LICENSE
Requires-Dist: requests
